_mscclpp.cpython-310-aarch64-linux-gnu.so
deep_gemm/__init__.py
deep_gemm/deep_gemm_cpp.abi3.so
deep_gemm/include/cute/algorithm/axpby.hpp
deep_gemm/include/cute/algorithm/clear.hpp
deep_gemm/include/cute/algorithm/cooperative_copy.hpp
deep_gemm/include/cute/algorithm/cooperative_gemm.hpp
deep_gemm/include/cute/algorithm/copy.hpp
deep_gemm/include/cute/algorithm/fill.hpp
deep_gemm/include/cute/algorithm/functional.hpp
deep_gemm/include/cute/algorithm/gemm.hpp
deep_gemm/include/cute/algorithm/prefer.hpp
deep_gemm/include/cute/algorithm/prefetch.hpp
deep_gemm/include/cute/algorithm/tensor_algorithms.hpp
deep_gemm/include/cute/algorithm/tensor_reduce.hpp
deep_gemm/include/cute/algorithm/tuple_algorithms.hpp
deep_gemm/include/cute/arch/cluster_sm100.hpp
deep_gemm/include/cute/arch/cluster_sm90.hpp
deep_gemm/include/cute/arch/config.hpp
deep_gemm/include/cute/arch/copy.hpp
deep_gemm/include/cute/arch/copy_sm100.hpp
deep_gemm/include/cute/arch/copy_sm100_tma.hpp
deep_gemm/include/cute/arch/copy_sm50.hpp
deep_gemm/include/cute/arch/copy_sm75.hpp
deep_gemm/include/cute/arch/copy_sm80.hpp
deep_gemm/include/cute/arch/copy_sm90.hpp
deep_gemm/include/cute/arch/copy_sm90_desc.hpp
deep_gemm/include/cute/arch/copy_sm90_tma.hpp
deep_gemm/include/cute/arch/mma.hpp
deep_gemm/include/cute/arch/mma_sm100.hpp
deep_gemm/include/cute/arch/mma_sm100_desc.hpp
deep_gemm/include/cute/arch/mma_sm100_umma.hpp
deep_gemm/include/cute/arch/mma_sm120.hpp
deep_gemm/include/cute/arch/mma_sm120_sparse.hpp
deep_gemm/include/cute/arch/mma_sm61.hpp
deep_gemm/include/cute/arch/mma_sm70.hpp
deep_gemm/include/cute/arch/mma_sm75.hpp
deep_gemm/include/cute/arch/mma_sm80.hpp
deep_gemm/include/cute/arch/mma_sm89.hpp
deep_gemm/include/cute/arch/mma_sm90.hpp
deep_gemm/include/cute/arch/mma_sm90_desc.hpp
deep_gemm/include/cute/arch/mma_sm90_gmma.hpp
deep_gemm/include/cute/arch/mma_sm90_gmma_ext.hpp
deep_gemm/include/cute/arch/mma_sm90_gmma_sparse.hpp
deep_gemm/include/cute/arch/mma_sm90_gmma_sparse_ext.hpp
sgl_kernel-0.3.21.dist-info/METADATA
sgl_kernel-0.3.21.dist-info/WHEEL
sgl_kernel-0.3.21.dist-info/licenses/LICENSE
sgl_kernel-0.3.21.dist-info/RECORD
