Metadata-Version: 2.1
Name: sgl-kernel
Version: 0.3.21
Summary: Kernel Library for SGLang
Author-Email: Yineng Zhang <me@zhyncs.com>
License:                                  Apache License
Classifier: Programming Language :: Python :: 3
Classifier: License :: OSI Approved :: Apache Software License
Classifier: Environment :: GPU :: NVIDIA CUDA
Project-URL: Homepage, https://github.com/sgl-project/sglang/tree/main/sgl-kernel
Project-URL: Bug Tracker, https://github.com/sgl-project/sglang/issues
Requires-Python: >=3.10
